{"homebrew_version":"1.3.4-58-ge322663","used_options":[],"unused_options":[],"built_as_bottle":true,"poured_from_bottle":true,"installed_as_dependency":true,"installed_on_request":true,"changed_files":["bin/g-ir-annotation-tool","bin/g-ir-scanner","INSTALL_RECEIPT.json","lib/gobject-introspection/giscanner/transformer.py","lib/gobject-introspection/giscanner/utils.py","lib/pkgconfig/gobject-introspection-1.0.pc","lib/pkgconfig/gobject-introspection-no-export-1.0.pc","share/gir-1.0/GIRepository-2.0.gir","share/gir-1.0/GLib-2.0.gir","share/gir-1.0/GModule-2.0.gir","share/gir-1.0/GObject-2.0.gir","share/gir-1.0/Gio-2.0.gir"],"time":1506999645,"source_modified_time":1506947095,"HEAD":null,"stdlib":null,"compiler":"clang","aliases":[],"runtime_dependencies":[{"full_name":"pkg-config","version":"0.29.2"},{"full_name":"gettext","version":"0.19.8.1"},{"full_name":"libffi","version":"3.2.1"},{"full_name":"pcre","version":"8.41"},{"full_name":"glib","version":"2.54.0"},{"full_name":"libpng","version":"1.6.32"},{"full_name":"freetype","version":"2.8.1"},{"full_name":"fontconfig","version":"2.12.6"},{"full_name":"pixman","version":"0.34.0"},{"full_name":"cairo","version":"1.14.10"}],"source":{"path":"/usr/local/Homebrew/Library/Taps/homebrew/homebrew-core/Formula/gobject-introspection.rb","tap":"homebrew/core","spec":"stable","versions":{"stable":"1.54.1","devel":null,"head":null,"version_scheme":0}}}